ftp_cloudfs-0.37.1.data/scripts/ftpcloudfs
ftpcloudfs/__init__.py
ftpcloudfs/chunkobject.py
ftpcloudfs/constants.py
ftpcloudfs/errors.py
ftpcloudfs/fs.py
ftpcloudfs/main.py
ftpcloudfs/monkeypatching.py
ftpcloudfs/server.py
ftpcloudfs/utils.py
ftp_cloudfs-0.37.1.dist-info/METADATA
ftp_cloudfs-0.37.1.dist-info/WHEEL
ftp_cloudfs-0.37.1.dist-info/top_level.txt
ftp_cloudfs-0.37.1.dist-info/RECORD
