Metadata-Version: 2.1
Name: ftp-cloudfs
Version: 0.37.1
Summary: FTP interface to OpenStack Object Storage (Swift)
Home-page: https://pypi.python.org/pypi/ftp-cloudfs/
Author: Chmouel Boudjnah
Author-email: chmouel@chmouel.com
License: MIT
Download-URL: http://pypi.python.org/packages/source/f/ftp-cloudfs/ftp-cloudfs-0.37.1.tar.gz
Platform: UNKNOWN
Classifier: Development Status :: 4 - Beta
Classifier: Environment :: Console
Classifier: Programming Language :: Python
Classifier: Operating System :: OS Independent
Classifier: Environment :: No Input/Output (Daemon)
Classifier: License :: OSI Approved :: MIT License
Requires-Dist: pyftpdlib (>=1.3.0)
Requires-Dist: python-swiftclient (>=2.1.0)
Requires-Dist: python-daemon (>=1.5.5)
Requires-Dist: python-memcached
